README.md
setup.py
db_tools/__init__.py
db_tools/db_meta.py
py_toolkit.egg-info/PKG-INFO
py_toolkit.egg-info/SOURCES.txt
py_toolkit.egg-info/dependency_links.txt
py_toolkit.egg-info/top_level.txt
py_toolkit.egg-info/zip-safe
tests/test_db_tools/__init__.py
tests/test_db_tools/test_db_meta.py